<?xml version="1.0" encoding="UTF-8" standalone="yes"?>
<!--

    Licensed to Apereo under one or more contributor license
    agreements. See the NOTICE file distributed with this work
    for additional information regarding copyright ownership.
    Apereo licenses this file to you under the Apache License,
    Version 2.0 (the "License"); you may not use this file
    except in compliance with the License.  You may obtain a
    copy of the License at the following location:

      http://www.apache.org/licenses/LICENSE-2.0

    Unless required by applicable law or agreed to in writing,
    software distributed under the License is distributed on an
    "AS IS" BASIS, WITHOUT WARRANTIES OR CONDITIONS OF ANY
    KIND, either express or implied.  See the License for the
    specific language governing permissions and limitations
    under the License.

-->
<resources xmlns="http://www.jasig.org/uportal/web/skin"
 xmlns:xsi="http://www.w3.org/2001/XMLSchema-instance"
 xsi:schemaLocation="http://www.jasig.org/uportal/web/skin https://source.jasig.org/schemas/resource-server/skin-configuration/skin-configuration-v1.2.xsd">

  <css>https://fonts.googleapis.com/css?family=Oxygen</css>

  <css included="plain">/ResourceServingWebapp/rs/normalize/2.1.2/normalize-2.1.2.css</css>
  <css included="aggregated">/ResourceServingWebapp/rs/normalize/2.1.2/normalize-2.1.2.min.css</css>

  <css included="plain">/ResourceServingWebapp/rs/fontawesome/4.0.3/css/font-awesome.css</css>
  <css included="aggregated">/ResourceServingWebapp/rs/fontawesome/4.0.3/css/font-awesome.min.css</css>

  <css included="plain" resource="true">/rs/bootstrap-plugins/accessibility/1.0.2/css/bootstrap-accessibility.css</css>
  <css included="aggregated" resource="true">/rs/bootstrap-plugins/accessibility/1.0.2/css/bootstrap-accessibility.min.css</css>

  <!-- Default jQuery UI theme.  Point this to a custom jQuery UI theme if desired. -->
  <css included="plain">/ResourceServingWebapp/rs/jqueryui/1.10.3/theme/smoothness/jquery-ui-1.10.3-smoothness.css</css>
  <css included="aggregated">/ResourceServingWebapp/rs/jqueryui/1.10.3/theme/smoothness/jquery-ui-1.10.3-smoothness.min.css</css>

  <!-- jsTree (entity-selector) -->
  <css included="plain" resource="true">/scripts/jstree/style.css</css>
  <css included="aggregated" resource="true">/scripts/jstree/style.min.css</css>

  <css import="true">../common/common_skin.xml</css>
  <!--
   | The skin is applied in lieu of using the Dynamic Skin Portlet.  Follow configuration information in skinList.xml
   | and disable Dynamic Skin Portlet.
   | This approach typically used by a non-tenant institution that copies defaultSkin and creates their own
   | institutional theme/skin.
   +-->
  <!--
  <css>../defaultSkin.css</css>
  -->

  <js import="true">../common/common_skin.xml</js>

</resources>
