<?xml version="1.0" encoding="UTF-8"?>
<!--

    Licensed to Jasig under one or more contributor license
    agreements. See the NOTICE file distributed with this work
    for additional information regarding copyright ownership.
    Jasig licenses this file to you under the Apache License,
    Version 2.0 (the "License"); you may not use this file
    except in compliance with the License. You may obtain a
    copy of the License at:

    http://www.apache.org/licenses/LICENSE-2.0

    Unless required by applicable law or agreed to in writing,
    software distributed under the License is distributed on
    an "AS IS" BASIS, WITHOUT WARRANTIES OR CONDITIONS OF ANY
    KIND, either express or implied. See the License for the
    specific language governing permissions and limitations
    under the License.

-->

<beans xmlns:xsi="http://www.w3.org/2001/XMLSchema-instance"
       xmlns="http://www.springframework.org/schema/beans" 
       xmlns:util="http://www.springframework.org/schema/util"
       xmlns:p="http://www.springframework.org/schema/p"
       xsi:schemaLocation="
           http://www.springframework.org/schema/beans http://www.springframework.org/schema/beans/spring-beans-3.1.xsd
           http://www.springframework.org/schema/util http://www.springframework.org/schema/util/spring-util-3.1.xsd">
    
    <!-- 
     | The concrete IPersonManager implementation to be used
     | drew (2012/07/26):  Use of RemoteUserSecurityContextFactory requires RemoteUserPersonManager
     +-->
   	<bean id="personManager" class="org.jasig.portal.security.provider.RemoteUserPersonManager" />


    <util:map id="profileKeyMappings">
        <entry key="desktop" value="default"/>
        <entry key="mobile" value="mobileDefault"/>
    </util:map>

    <bean id="profileMapper" class="org.jasig.portal.layout.ChainingProfileMapperImpl">
        <property name="defaultProfileName" value="default" />
        <property name="subMappers">
            <util:list>
                <ref bean="sessionAttributeProfileMapper" />
                <ref bean="userAgentProfileMapper" />
            </util:list>
        </property>
    </bean>
    
    <bean id="sessionAttributeProfileMapper" class="org.jasig.portal.layout.SessionAttributeProfileMapperImpl"
        p:mappings-ref="profileKeyMappings"/>
    
    <bean id="userAgentProfileMapper" class="org.jasig.portal.layout.UserAgentProfileMapper">
        <property name="mappings">
            <list>
                <!-- Apple iPad -->
                <bean class="org.jasig.portal.layout.UserAgentProfileMapper.Mapping">
                    <property name="pattern" value=".*iPad.*" />
                    <property name="profileName" value="default" />
                </bean>
                <!-- Apple iPhone -->
                <bean class="org.jasig.portal.layout.UserAgentProfileMapper.Mapping">
                    <property name="pattern" value=".*iPhone.*" />
                    <property name="profileName" value="mobileDefault" />
                </bean>
                <!-- Android -->
                <bean class="org.jasig.portal.layout.UserAgentProfileMapper.Mapping">
                    <property name="pattern" value=".*Android.*Mobile.*" />
                    <property name="profileName" value="mobileDefault" />
                </bean>
                <!-- Palm Pre -->
                <bean class="org.jasig.portal.layout.UserAgentProfileMapper.Mapping">
                    <property name="pattern" value=".*Safari.*Pre.*" />
                    <property name="profileName" value="mobileDefault" />
                </bean>
                <!-- Nokia S60 web browser -->
                <bean class="org.jasig.portal.layout.UserAgentProfileMapper.Mapping">
                    <property name="pattern" value=".*Nokia.*AppleWebKit.*" />
                    <property name="profileName" value="mobileDefault" />
                </bean>
                <!-- Blackberry web browser -->
                <bean class="org.jasig.portal.layout.UserAgentProfileMapper.Mapping">
                    <property name="pattern" value=".*Black[Bb]erry.*" />
                    <property name="profileName" value="mobileDefault" />
                </bean>
                <!-- Opera Mobile web browser -->
                <bean class="org.jasig.portal.layout.UserAgentProfileMapper.Mapping">
                    <property name="pattern" value=".*Opera Mobile.*" />
                    <property name="profileName" value="mobileDefault" />
                </bean>
            </list>
        </property>
    </bean>

    <util:list id="directoryQueryAttributes">
        <value>givenName</value>
        <value>sn</value>
    </util:list>

    <util:map id="directoryDisplayAttributes">
        <entry key="title" value="GENERIC"/>
        <entry key="department" value="GENERIC"/>
        <entry key="organization" value="GENERIC"/>
        <entry key="mail" value="EMAIL"/>
        <entry key="telephoneNumber" value="PHONE"/>
        <entry key="postalAddress" value="MAP"/>
    </util:map>

    <!-- Form inputs for local account editing.  These fields will be filtered
        according to user permissions. -->
    <util:list id="accountEditAttributes">
        <bean class="org.jasig.portal.portlets.account.PreferenceInputFactory"
            factory-method="createSingleTextPreference">
            <constructor-arg value="title"/>
            <constructor-arg value="attribute.displayName.title"/>
        </bean>
        <bean class="org.jasig.portal.portlets.account.PreferenceInputFactory"
            factory-method="createSingleTextPreference">
            <constructor-arg value="department"/>
            <constructor-arg value="attribute.displayName.department"/>
        </bean>
        <bean class="org.jasig.portal.portlets.account.PreferenceInputFactory"
            factory-method="createSingleTextPreference">
            <constructor-arg value="organization"/>
            <constructor-arg value="attribute.displayName.organization"/>
        </bean>
        <bean class="org.jasig.portal.portlets.account.PreferenceInputFactory"
            factory-method="createSingleTextPreference">
            <constructor-arg value="mail"/>
            <constructor-arg value="attribute.displayName.mail"/>
        </bean>
        <bean class="org.jasig.portal.portlets.account.PreferenceInputFactory"
            factory-method="createSingleTextPreference">
            <constructor-arg value="telephoneNumber"/>
            <constructor-arg value="attribute.displayName.telephoneNumber"/>
        </bean>
        
        <!-- 
         | Attributes for SSP Permissions:
         | These attributes place users in PAGS groups, which are themselves 
         | members of similarly-named database (local) groups.  The local groups 
         | are referenced using <security-role-ref> elements in the SSP portlet 
         | app.
         +-->
        <bean class="org.jasig.portal.portlets.account.PreferenceInputFactory"
            factory-method="createMultiChoicePreference">
            <!-- String name -->
            <constructor-arg value="SSP_ROLES"/>
            <!-- String label (optionally a key for messages.properties) -->
            <constructor-arg value="SSP Role(s)"/>
            <!-- SingleChoiceDisplay displayType -->
            <constructor-arg value="SELECT"/>
			<!-- List<Option> options -->
            <constructor-arg>
            	<list>
            		<bean class="org.jasig.portal.portletpublishing.xml.Option">
            			<property name="label" value="[NONE]" />
            			<property name="value" value="" />
            		</bean>
            		<bean class="org.jasig.portal.portletpublishing.xml.Option">
            			<property name="label" value="Administrator" />
            			<property name="value" value="SSP_ADMINISTRATOR" />
            		</bean>
            		<bean class="org.jasig.portal.portletpublishing.xml.Option">
            			<property name="label" value="Coach" />
            			<property name="value" value="SSP_COACH" />
            		</bean>
            		<bean class="org.jasig.portal.portletpublishing.xml.Option">
            			<property name="label" value="Developer" />
            			<property name="value" value="SSP_DEVELOPER" />
            		</bean>
            		<bean class="org.jasig.portal.portletpublishing.xml.Option">
            			<property name="label" value="Faculty" />
            			<property name="value" value="SSP_FACULTY" />
            		</bean>
            		<bean class="org.jasig.portal.portletpublishing.xml.Option">
            			<property name="label" value="Manager" />
            			<property name="value" value="SSP_MANAGER" />
            		</bean>
                    <bean class="org.jasig.portal.portletpublishing.xml.Option">
            			<property name="label" value="MAP Template Admin" />
            			<property name="value" value="SSP_MAP_TEMPLATE_ADMIN" />
            		</bean>
            		<bean class="org.jasig.portal.portletpublishing.xml.Option">
            			<property name="label" value="Support Staff" />
            			<property name="value" value="SSP_SUPPORT_STAFF" />
            		</bean>
            		<bean class="org.jasig.portal.portletpublishing.xml.Option">
            			<property name="label" value="Student" />
            			<property name="value" value="SSP_STUDENT" />
            		</bean>            		
            	</list>
            </constructor-arg>
            <!-- String defaultValue -->
            <constructor-arg value="FALSE"/>
        </bean>
        <bean class="org.jasig.portal.portlets.account.PreferenceInputFactory"
            factory-method="createSingleChoicePreference">
            <!-- String name -->
            <constructor-arg value="DATA_ACADEMIC_RESOURCE_CENTER"/>
            <!-- String label (optionally a key for messages.properties) -->
            <constructor-arg value="DATA_ACADEMIC_RESOURCE_CENTER"/>
            <!-- SingleChoiceDisplay displayType -->
            <constructor-arg value="SELECT"/>
			<!-- List<Option> options -->
            <constructor-arg>
            	<list>
            		<bean class="org.jasig.portal.portletpublishing.xml.Option">
            			<property name="label" value="FALSE" />
            			<property name="value" value="FALSE" />
            		</bean>
            		<bean class="org.jasig.portal.portletpublishing.xml.Option">
            			<property name="label" value="TRUE" />
            			<property name="value" value="TRUE" />
            		</bean>
            	</list>
            </constructor-arg>
            <!-- String defaultValue -->
            <constructor-arg value="FALSE"/>
        </bean>
        <bean class="org.jasig.portal.portlets.account.PreferenceInputFactory"
            factory-method="createSingleChoicePreference">
            <!-- String name -->
            <constructor-arg value="DATA_COUNSELING_SERVICES"/>
            <!-- String label (optionally a key for messages.properties) -->
            <constructor-arg value="DATA_COUNSELING_SERVICES"/>
            <!-- SingleChoiceDisplay displayType -->
            <constructor-arg value="SELECT"/>
			<!-- List<Option> options -->
            <constructor-arg>
            	<list>
            		<bean class="org.jasig.portal.portletpublishing.xml.Option">
            			<property name="label" value="FALSE" />
            			<property name="value" value="FALSE" />
            		</bean>
            		<bean class="org.jasig.portal.portletpublishing.xml.Option">
            			<property name="label" value="TRUE" />
            			<property name="value" value="TRUE" />
            		</bean>
            	</list>
            </constructor-arg>
            <!-- String defaultValue -->
            <constructor-arg value="FALSE"/>
        </bean>
        <bean class="org.jasig.portal.portlets.account.PreferenceInputFactory"
            factory-method="createSingleChoicePreference">
            <!-- String name -->
            <constructor-arg value="DATA_DISABILITY"/>
            <!-- String label (optionally a key for messages.properties) -->
            <constructor-arg value="DATA_DISABILITY"/>
            <!-- SingleChoiceDisplay displayType -->
            <constructor-arg value="SELECT"/>
			<!-- List<Option> options -->
            <constructor-arg>
            	<list>
            		<bean class="org.jasig.portal.portletpublishing.xml.Option">
            			<property name="label" value="FALSE" />
            			<property name="value" value="FALSE" />
            		</bean>
            		<bean class="org.jasig.portal.portletpublishing.xml.Option">
            			<property name="label" value="TRUE" />
            			<property name="value" value="TRUE" />
            		</bean>
            	</list>
            </constructor-arg>
            <!-- String defaultValue -->
            <constructor-arg value="FALSE"/>
        </bean>
        <bean class="org.jasig.portal.portlets.account.PreferenceInputFactory"
            factory-method="createSingleChoicePreference">
            <!-- String name -->
            <constructor-arg value="DATA_DISPLACED_WORKERS"/>
            <!-- String label (optionally a key for messages.properties) -->
            <constructor-arg value="DATA_DISPLACED_WORKERS"/>
            <!-- SingleChoiceDisplay displayType -->
            <constructor-arg value="SELECT"/>
			<!-- List<Option> options -->
            <constructor-arg>
            	<list>
            		<bean class="org.jasig.portal.portletpublishing.xml.Option">
            			<property name="label" value="FALSE" />
            			<property name="value" value="FALSE" />
            		</bean>
            		<bean class="org.jasig.portal.portletpublishing.xml.Option">
            			<property name="label" value="TRUE" />
            			<property name="value" value="TRUE" />
            		</bean>
            	</list>
            </constructor-arg>
            <!-- String defaultValue -->
            <constructor-arg value="FALSE"/>
        </bean>
        <bean class="org.jasig.portal.portlets.account.PreferenceInputFactory"
            factory-method="createSingleChoicePreference">
            <!-- String name -->
            <constructor-arg value="DATA_EARLY_ALERT"/>
            <!-- String label (optionally a key for messages.properties) -->
            <constructor-arg value="DATA_EARLY_ALERT"/>
            <!-- SingleChoiceDisplay displayType -->
            <constructor-arg value="SELECT"/>
			<!-- List<Option> options -->
            <constructor-arg>
            	<list>
            		<bean class="org.jasig.portal.portletpublishing.xml.Option">
            			<property name="label" value="FALSE" />
            			<property name="value" value="FALSE" />
            		</bean>
            		<bean class="org.jasig.portal.portletpublishing.xml.Option">
            			<property name="label" value="TRUE" />
            			<property name="value" value="TRUE" />
            		</bean>
            	</list>
            </constructor-arg>
            <!-- String defaultValue -->
            <constructor-arg value="FALSE"/>
        </bean>
        <bean class="org.jasig.portal.portlets.account.PreferenceInputFactory"
            factory-method="createSingleChoicePreference">
            <!-- String name -->
            <constructor-arg value="DATA_ENGLISH_SECOND_LANGUAGE"/>
            <!-- String label (optionally a key for messages.properties) -->
            <constructor-arg value="DATA_ENGLISH_SECOND_LANGUAGE"/>
            <!-- SingleChoiceDisplay displayType -->
            <constructor-arg value="SELECT"/>
			<!-- List<Option> options -->
            <constructor-arg>
            	<list>
            		<bean class="org.jasig.portal.portletpublishing.xml.Option">
            			<property name="label" value="FALSE" />
            			<property name="value" value="FALSE" />
            		</bean>
            		<bean class="org.jasig.portal.portletpublishing.xml.Option">
            			<property name="label" value="TRUE" />
            			<property name="value" value="TRUE" />
            		</bean>
            	</list>
            </constructor-arg>
            <!-- String defaultValue -->
            <constructor-arg value="FALSE"/>
        </bean>
        <bean class="org.jasig.portal.portlets.account.PreferenceInputFactory"
            factory-method="createSingleChoicePreference">
            <!-- String name -->
            <constructor-arg value="DATA_FAST_FORWARD"/>
            <!-- String label (optionally a key for messages.properties) -->
            <constructor-arg value="DATA_FAST_FORWARD"/>
            <!-- SingleChoiceDisplay displayType -->
            <constructor-arg value="SELECT"/>
			<!-- List<Option> options -->
            <constructor-arg>
            	<list>
            		<bean class="org.jasig.portal.portletpublishing.xml.Option">
            			<property name="label" value="FALSE" />
            			<property name="value" value="FALSE" />
            		</bean>
            		<bean class="org.jasig.portal.portletpublishing.xml.Option">
            			<property name="label" value="TRUE" />
            			<property name="value" value="TRUE" />
            		</bean>
            	</list>
            </constructor-arg>
            <!-- String defaultValue -->
            <constructor-arg value="FALSE"/>
        </bean>
        <bean class="org.jasig.portal.portlets.account.PreferenceInputFactory"
            factory-method="createSingleChoicePreference">
            <!-- String name -->
            <constructor-arg value="DATA_INDIVIDUALIZED_LEARNING_PLAN"/>
            <!-- String label (optionally a key for messages.properties) -->
            <constructor-arg value="DATA_INDIVIDUALIZED_LEARNING_PLAN"/>
            <!-- SingleChoiceDisplay displayType -->
            <constructor-arg value="SELECT"/>
			<!-- List<Option> options -->
            <constructor-arg>
            	<list>
            		<bean class="org.jasig.portal.portletpublishing.xml.Option">
            			<property name="label" value="FALSE" />
            			<property name="value" value="FALSE" />
            		</bean>
            		<bean class="org.jasig.portal.portletpublishing.xml.Option">
            			<property name="label" value="TRUE" />
            			<property name="value" value="TRUE" />
            		</bean>
            	</list>
            </constructor-arg>
            <!-- String defaultValue -->
            <constructor-arg value="FALSE"/>
        </bean>

    </util:list>
    
    <!-- Spring mail-sending service -->
    <bean id="passwordResetMailSender" class="org.springframework.mail.javamail.JavaMailSenderImpl">
        <property name="host" value="${org.jasig.portal.email.host:localhost}" />
        <property name="port" value="${org.jasig.portal.email.port:25}" />
        <property name="protocol" value="${org.jasig.portal.email.protocol:smtp}" />
    </bean>
    
    <bean id="portalEmailAddress" class="java.lang.String">
        <constructor-arg value="${org.jasig.portal.email.fromAddress}"/>
    </bean>
    
</beans>
